<?xml version="1.0" encoding="UTF-8"?>
<ProtocolCommandItems><CommandItem xmlns:xsi="http://www.w3.org/2001/XMLSchema-instance" xsi:type="java:org.exolab.castor.mapping.MapItem"><key xsi:type="java:java.lang.String">10040001</key><value CommandCode="10040001" xsi:type="CommandItem"><DataItem xsi:type="java:org.exolab.castor.mapping.MapItem"><key xsi:type="java:java.lang.String">1004000102</key><value Length="1" Format="BIN" DataItemCode="1004000102" GroupCode="" length="1" xsi:type="protocol-data-item"><group-code></group-code><data-item-code>1004000102</data-item-code><format>BIN</format></value></DataItem><DataItem xsi:type="java:org.exolab.castor.mapping.MapItem"><key xsi:type="java:java.lang.String">1004000103</key><value Length="1" Format="BIN" DataItemCode="1004000103" GroupCode="" length="1" xsi:type="protocol-data-item"><group-code></group-code><data-item-code>1004000103</data-item-code><format>BIN</format></value></DataItem><DataItem xsi:type="java:org.exolab.castor.mapping.MapItem"><key xsi:type="java:java.lang.String">1004000101</key><value Length="1" Format="BIN" DataItemCode="1004000101" GroupCode="" length="1" xsi:type="protocol-data-item"><group-code></group-code><data-item-code>1004000101</data-item-code><format>BIN</format></value></DataItem><data-items xsi:type="java:org.exolab.castor.mapping.MapItem"><key xsi:type="java:java.lang.String">1004000102</key><value Length="1" Format="BIN" DataItemCode="1004000102" GroupCode="" length="1" xsi:type="protocol-data-item"><group-code></group-code><data-item-code>1004000102</data-item-code><format>BIN</format></value></data-items><data-items xsi:type="java:org.exolab.castor.mapping.MapItem"><key xsi:type="java:java.lang.String">1004000103</key><value Length="1" Format="BIN" DataItemCode="1004000103" GroupCode="" length="1" xsi:type="protocol-data-item"><group-code></group-code><data-item-code>1004000103</data-item-code><format>BIN</format></value></data-items><data-items xsi:type="java:org.exolab.castor.mapping.MapItem"><key xsi:type="java:java.lang.String">1004000101</key><value Length="1" Format="BIN" DataItemCode="1004000101" GroupCode="" length="1" xsi:type="protocol-data-item"><group-code></group-code><data-item-code>1004000101</data-item-code><format>BIN</format></value></data-items><command-code>10040001</command-code></value></CommandItem><command-items xmlns:xsi="http://www.w3.org/2001/XMLSchema-instance" xsi:type="java:org.exolab.castor.mapping.MapItem"><key xsi:type="java:java.lang.String">10040001</key><value CommandCode="10040001" xsi:type="CommandItem"><DataItem xsi:type="java:org.exolab.castor.mapping.MapItem"><key xsi:type="java:java.lang.String">1004000102</key><value Length="1" Format="BIN" DataItemCode="1004000102" GroupCode="" length="1" xsi:type="protocol-data-item"><group-code></group-code><data-item-code>1004000102</data-item-code><format>BIN</format></value></DataItem><DataItem xsi:type="java:org.exolab.castor.mapping.MapItem"><key xsi:type="java:java.lang.String">1004000103</key><value Length="1" Format="BIN" DataItemCode="1004000103" GroupCode="" length="1" xsi:type="protocol-data-item"><group-code></group-code><data-item-code>1004000103</data-item-code><format>BIN</format></value></DataItem><DataItem xsi:type="java:org.exolab.castor.mapping.MapItem"><key xsi:type="java:java.lang.String">1004000101</key><value Length="1" Format="BIN" DataItemCode="1004000101" GroupCode="" length="1" xsi:type="protocol-data-item"><group-code></group-code><data-item-code>1004000101</data-item-code><format>BIN</format></value></DataItem><data-items xsi:type="java:org.exolab.castor.mapping.MapItem"><key xsi:type="java:java.lang.String">1004000102</key><value Length="1" Format="BIN" DataItemCode="1004000102" GroupCode="" length="1" xsi:type="protocol-data-item"><group-code></group-code><data-item-code>1004000102</data-item-code><format>BIN</format></value></data-items><data-items xsi:type="java:org.exolab.castor.mapping.MapItem"><key xsi:type="java:java.lang.String">1004000103</key><value Length="1" Format="BIN" DataItemCode="1004000103" GroupCode="" length="1" xsi:type="protocol-data-item"><group-code></group-code><data-item-code>1004000103</data-item-code><format>BIN</format></value></data-items><data-items xsi:type="java:org.exolab.castor.mapping.MapItem"><key xsi:type="java:java.lang.String">1004000101</key><value Length="1" Format="BIN" DataItemCode="1004000101" GroupCode="" length="1" xsi:type="protocol-data-item"><group-code></group-code><data-item-code>1004000101</data-item-code><format>BIN</format></value></data-items><command-code>10040001</command-code></value></command-items></ProtocolCommandItems>